MANIFEST.in
README.rst
setup.py
mezzanine_grappelli/__init__.py
mezzanine_grappelli/models.py
mezzanine_grappelli.egg-info/PKG-INFO
mezzanine_grappelli.egg-info/SOURCES.txt
mezzanine_grappelli.egg-info/dependency_links.txt
mezzanine_grappelli.egg-info/not-zip-safe
mezzanine_grappelli.egg-info/requires.txt
mezzanine_grappelli.egg-info/top_level.txt
mezzanine_grappelli/static/mezzanine/js/tinymce_setup.js
mezzanine_grappelli/static/mezzanine/js/admin/navigation.js
mezzanine_grappelli/static/mezzanine_grappelli/css/admin/mezzanine_grappelli.css
mezzanine_grappelli/static/mezzanine_grappelli/css/admin/tiny_mce.css
mezzanine_grappelli/templates/admin/base_site.html
mezzanine_grappelli/templates/admin/index.html
mezzanine_grappelli/templates/admin/login.html
mezzanine_grappelli/templates/admin/includes/app_list.html
mezzanine_grappelli/templates/admin/includes/dropdown_menu.html
mezzanine_grappelli/templates/admin/includes/quick_blog.html
mezzanine_grappelli/templates/admin/includes/recent_actions.html
mezzanine_grappelli/templates/admin/includes/recent_comments.html
mezzanine_grappelli/templates/admin/pages/page/change_list.html
mezzanine_grappelli/templates/includes/editable_loader.html