Metadata-Version: 1.1
Name: mezzanine-grappelli
Version: 0.1.0
Summary: mezzanine-grappelli makes Mezzanine ♥ Grappelli
Home-page: https://github.com/sephii/mezzanine-grappelli/
Author: Sylvain Fankhauser
Author-email: sylvain@fankhauser.name
License: BSD
Platform: UNKNOWN
Classifier: Development Status :: 4 - Beta
Classifier: Environment :: Web Environment
Classifier: Framework :: Django
Classifier: Intended Audience :: Developers
Classifier: License :: OSI Approved :: BSD License
Classifier: Operating System :: OS Independent
